CGDs/__init__.py
CGDs/acgd.py
CGDs/cg_torch.py
CGDs/cgd.py
CGDs/cgd_utils.py
CGDs/distributed.py
CGDs/gmres_acgd.py
CGDs/gmres_torch.py
CGDs-0.4.5.dist-info/LICENSE
CGDs-0.4.5.dist-info/METADATA
CGDs-0.4.5.dist-info/WHEEL
CGDs-0.4.5.dist-info/top_level.txt
CGDs-0.4.5.dist-info/RECORD
