Metadata-Version: 2.1
Name: CGDs
Version: 0.4.5
Summary: Adaptive Competitive Gradient Descent optimizer
Home-page: https://github.com/devzhk/cgds-package
Author: Hongkai Zheng
Author-email: devzhk@gmail.com
Project-URL: Bug Tracker, https://github.com/devzhk/cgds-package/issues
Classifier: Programming Language :: Python :: 3
Classifier: License :: OSI Approved :: MIT License
Classifier: Operating System :: OS Independent
Requires-Python: >=3.6
License-File: LICENSE
